README.rst
setup.py
hashdb2/__init__.py
hashdb2/command_comp.py
hashdb2/command_hash.py
hashdb2/command_line.py
hashdb2/escape.py
hashdb2/hash.py
hashdb2/orm.py
hashdb2/walk.py
hashdb2.egg-info/PKG-INFO
hashdb2.egg-info/SOURCES.txt
hashdb2.egg-info/dependency_links.txt
hashdb2.egg-info/entry_points.txt
hashdb2.egg-info/not-zip-safe
hashdb2.egg-info/requires.txt
hashdb2.egg-info/top_level.txt