Metadata-Version: 1.1
Name: hashdb2
Version: 1.0
Summary: HashDb2 provides a simple method for executing commands based on matched files
Home-page: https://github.com/WHenderson/HashDb
Author: Will Henderson
Author-email: whenderson.github@gmail.com
License: Apache 2.0
Keywords: file matching comparison same identical duplicate duplicates
Platform: UNKNOWN
Classifier: Development Status :: 5 - Production/Stable
Classifier: Programming Language :: Python :: 3 :: Only
Classifier: Programming Language :: Python :: 3.5
Classifier: Programming Language :: Python :: 3.6
Classifier: License :: OSI Approved :: Apache Software License
Classifier: Topic :: System :: Filesystems
Classifier: Topic :: Database
Classifier: Topic :: Utilities
